AUTHORS.rst
CONTRIBUTING.rst
HISTORY.rst
LICENSE
MANIFEST.in
README.rst
setup.cfg
setup.py
docs/Makefile
docs/authors.rst
docs/conf.py
docs/contributing.rst
docs/history.rst
docs/index.rst
docs/installation.rst
docs/make.bat
docs/readme.rst
docs/usage.rst
ptm_annotator/GraphAssembly.py
ptm_annotator/GraphCalculation.py
ptm_annotator/__init__.py
ptm_annotator/protein_plot.py
ptm_annotator/ptm_annotator.py
ptm_annotator/ptm_processor.py
ptm_annotator/thermo_file_converter.py
ptm_annotator.egg-info/PKG-INFO
ptm_annotator.egg-info/SOURCES.txt
ptm_annotator.egg-info/dependency_links.txt
ptm_annotator.egg-info/not-zip-safe
ptm_annotator.egg-info/top_level.txt
tests/TestCommand.txt
tests/__init__.py
tests/test_GraphCalculate.py
tests/test_ptm-annotator.py