Metadata-Version: 1.1
Name: ptm-annotator
Version: 0.2.0
Summary: PTM-annotator is an open source cross-platform Python library to annotate and graphically analyze PTM search results.
Home-page: https://github.com/gtg269c/ptm-annotator
Author: Amin A Momin
Author-email: momin.amin@gmail.com
License: ISCL
Keywords: ptm_annotator
Platform: UNKNOWN
Classifier: Development Status :: 2 - Pre-Alpha
Classifier: Intended Audience :: Developers
Classifier: License :: OSI Approved :: ISC License (ISCL)
Classifier: Natural Language :: English
Classifier: Programming Language :: Python :: 2
Classifier: Programming Language :: Python :: 2.6
Classifier: Programming Language :: Python :: 2.7
Classifier: Programming Language :: Python :: 3
Classifier: Programming Language :: Python :: 3.3
Classifier: Programming Language :: Python :: 3.4
Classifier: Programming Language :: Python :: 3.5
